odoo/addons/base_portal_type/README.rst
odoo/addons/base_portal_type/__init__.py
odoo/addons/base_portal_type/__manifest__.py
odoo/addons/base_portal_type/data/ir_module_category.xml
odoo/addons/base_portal_type/demo/res_groups.xml
odoo/addons/base_portal_type/i18n/base_portal_type.pot
odoo/addons/base_portal_type/i18n/it.po
odoo/addons/base_portal_type/models/__init__.py
odoo/addons/base_portal_type/models/res_groups.py
odoo/addons/base_portal_type/readme/CONTRIBUTORS.rst
odoo/addons/base_portal_type/readme/DESCRIPTION.rst
odoo/addons/base_portal_type/readme/ROADMAP.rst
odoo/addons/base_portal_type/readme/USAGE.rst
odoo/addons/base_portal_type/static/description/icon.png
odoo/addons/base_portal_type/static/description/index.html
odoo/addons/base_portal_type/tests/__init__.py
odoo/addons/base_portal_type/tests/test_base_portal_type.py
odoo_addon_base_portal_type-16.0.1.0.0.5.dist-info/METADATA
odoo_addon_base_portal_type-16.0.1.0.0.5.dist-info/WHEEL
odoo_addon_base_portal_type-16.0.1.0.0.5.dist-info/top_level.txt
odoo_addon_base_portal_type-16.0.1.0.0.5.dist-info/RECORD
